[
null,
{
  "id": 1,
  "name": "Health Potion",
  "description": "A basic healing potion that restores HP.",
  "iconIndex": 0,
  "price": 50,
  "consumable": true,
  "damage": {"type": 3, "elementId": 0, "formula": "250", "variance": 20, "critical": false},
  "effects": [],
  "repeats": 1,
  "tpGain": 0,
  "hitType": 0,
  "animationId": 0,
  "successRate": 100,
  "speed": 0,
  "scope": 1,
  "occasion": 0,
  "note": "Basic healing item available in most shops",
  "etypeId": 0
},
{
  "id": 2,
  "name": "Mana Potion",
  "description": "A basic mana potion that restores MP.",
  "iconIndex": 1,
  "price": 40,
  "consumable": true,
  "damage": {"type": 4, "elementId": 0, "formula": "100", "variance": 20, "critical": false},
  "effects": [],
  "repeats": 1,
  "tpGain": 0,
  "hitType": 0,
  "animationId": 0,
  "successRate": 100,
  "speed": 0,
  "scope": 1,
  "occasion": 0,
  "note": "Basic mana restoration item",
  "etypeId": 0
},
{
  "id": 10,
  "name": "Cultivation Pill - Foundation",
  "description": "A basic cultivation pill that aids in spiritual foundation building. Grants experience when consumed.",
  "iconIndex": 10,
  "price": 200,
  "consumable": true,
  "damage": {"type": 0, "elementId": 0, "formula": "0", "variance": 0, "critical": false},
  "effects": [{"code": 44, "dataId": 0, "value1": 100, "value2": 0}],
  "repeats": 1,
  "tpGain": 0,
  "hitType": 0,
  "animationId": 0,
  "successRate": 100,
  "speed": 0,
  "scope": 1,
  "occasion": 0,
  "note": "Grants 100 experience points - aids in early cultivation",
  "etypeId": 0
},
{
  "id": 11,
  "name": "Qi Gathering Pill",
  "description": "A refined pill that helps gather and refine spiritual qi. Used by 8th Grade Warriors.",
  "iconIndex": 11,
  "price": 500,
  "consumable": true,
  "damage": {"type": 0, "elementId": 0, "formula": "0", "variance": 0, "critical": false},
  "effects": [{"code": 44, "dataId": 0, "value1": 250, "value2": 0}],
  "repeats": 1,
  "tpGain": 0,
  "hitType": 0,
  "animationId": 0,
  "successRate": 100,
  "speed": 0,
  "scope": 1,
  "occasion": 0,
  "note": "Grants 250 experience points - for Refining Qi stage",
  "etypeId": 0
},
{
  "id": 12,
  "name": "Spirit Refining Elixir",
  "description": "A precious elixir that enhances spiritual perception and intuition. Favored by 7th Grade cultivators.",
  "iconIndex": 12,
  "price": 1000,
  "consumable": true,
  "damage": {"type": 0, "elementId": 0, "formula": "0", "variance": 0, "critical": false},
  "effects": [{"code": 44, "dataId": 0, "value1": 500, "value2": 0}],
  "repeats": 1,
  "tpGain": 0,
  "hitType": 0,
  "animationId": 0,
  "successRate": 100,
  "speed": 0,
  "scope": 1,
  "occasion": 0,
  "note": "Grants 500 experience points - for Refining Spirit stage",
  "etypeId": 0
},
{
  "id": 13,
  "name": "Golden Core Essence",
  "description": "Extremely rare essence used in forming the Taoist Golden Core. Only for advanced cultivators.",
  "iconIndex": 13,
  "price": 5000,
  "consumable": true,
  "damage": {"type": 0, "elementId": 0, "formula": "0", "variance": 0, "critical": false},
  "effects": [{"code": 44, "dataId": 0, "value1": 1500, "value2": 0}],
  "repeats": 1,
  "tpGain": 0,
  "hitType": 0,
  "animationId": 0,
  "successRate": 100,
  "speed": 0,
  "scope": 1,
  "occasion": 0,
  "note": "Grants 1500 experience points - for Golden Core formation",
  "etypeId": 0
},
{
  "id": 20,
  "name": "Confucian Wisdom Scroll",
  "description": "A scroll containing profound Confucian teachings. Enhances moral cultivation and scholarly knowledge.",
  "iconIndex": 20,
  "price": 300,
  "consumable": true,
  "damage": {"type": 0, "elementId": 0, "formula": "0", "variance": 0, "critical": false},
  "effects": [{"code": 44, "dataId": 0, "value1": 200, "value2": 0}],
  "repeats": 1,
  "tpGain": 0,
  "hitType": 0,
  "animationId": 0,
  "successRate": 100,
  "speed": 0,
  "scope": 1,
  "occasion": 0,
  "note": "Grants 200 experience points - Confucian cultivation aid",
  "etypeId": 0
},
{
  "id": 21,
  "name": "Buddhist Meditation Beads",
  "description": "Sacred beads blessed by high monks. Aids in meditation and spiritual enlightenment.",
  "iconIndex": 21,
  "price": 400,
  "consumable": true,
  "damage": {"type": 0, "elementId": 0, "formula": "0", "variance": 0, "critical": false},
  "effects": [{"code": 44, "dataId": 0, "value1": 300, "value2": 0}],
  "repeats": 1,
  "tpGain": 0,
  "hitType": 0,
  "animationId": 0,
  "successRate": 100,
  "speed": 0,
  "scope": 1,
  "occasion": 0,
  "note": "Grants 300 experience points - Buddhist cultivation aid",
  "etypeId": 0
},
{
  "id": 30,
  "name": "Guardian's Badge",
  "description": "Official badge of the Night Watchmen. Provides authority and access to restricted areas.",
  "iconIndex": 30,
  "price": 0,
  "consumable": false,
  "damage": {"type": 0, "elementId": 0, "formula": "0", "variance": 0, "critical": false},
  "effects": [],
  "repeats": 1,
  "tpGain": 0,
  "hitType": 0,
  "animationId": 0,
  "successRate": 100,
  "speed": 0,
  "scope": 0,
  "occasion": 3,
  "note": "Key item - proves Guardian membership and authority",
  "etypeId": 0
},
{
  "id": 31,
  "name": "Investigation Kit",
  "description": "A set of modern investigative tools adapted for the Dafeng Dynasty. Unique to Xu Qi'an.",
  "iconIndex": 31,
  "price": 0,
  "consumable": false,
  "damage": {"type": 0, "elementId": 0, "formula": "0", "variance": 0, "critical": false},
  "effects": [],
  "repeats": 1,
  "tpGain": 0,
  "hitType": 0,
  "animationId": 0,
  "successRate": 100,
  "speed": 0,
  "scope": 0,
  "occasion": 3,
  "note": "Key item - enables advanced investigation techniques",
  "etypeId": 0
},
{
  "id": 32,
  "name": "Royal Seal",
  "description": "Princess Lin'an's personal seal. Grants imperial authority for official matters.",
  "iconIndex": 32,
  "price": 0,
  "consumable": false,
  "damage": {"type": 0, "elementId": 0, "formula": "0", "variance": 0, "critical": false},
  "effects": [],
  "repeats": 1,
  "tpGain": 0,
  "hitType": 0,
  "animationId": 0,
  "successRate": 100,
  "speed": 0,
  "scope": 0,
  "occasion": 3,
  "note": "Key item - enables use of imperial authority",
  "etypeId": 0
},
{
  "id": 33,
  "name": "Strategic Manual",
  "description": "Wei Yuan's personal collection of military strategies and tactical knowledge.",
  "iconIndex": 33,
  "price": 0,
  "consumable": false,
  "damage": {"type": 0, "elementId": 0, "formula": "0", "variance": 0, "critical": false},
  "effects": [],
  "repeats": 1,
  "tpGain": 0,
  "hitType": 0,
  "animationId": 0,
  "successRate": 100,
  "speed": 0,
  "scope": 0,
  "occasion": 3,
  "note": "Key item - unlocks advanced tactical abilities",
  "etypeId": 0
},
{
  "id": 40,
  "name": "Sangbo Lake Fragment",
  "description": "A mysterious fragment from the Sangbo Lake explosion. Contains unknown supernatural power.",
  "iconIndex": 40,
  "price": 0,
  "consumable": false,
  "damage": {"type": 0, "elementId": 0, "formula": "0", "variance": 0, "critical": false},
  "effects": [],
  "repeats": 1,
  "tpGain": 0,
  "hitType": 0,
  "animationId": 0,
  "successRate": 100,
  "speed": 0,
  "scope": 0,
  "occasion": 3,
  "note": "Key item - central to the main story mystery",
  "etypeId": 0
},
{
  "id": 41,
  "name": "Taoist Talisman",
  "description": "A protective talisman inscribed with Taoist symbols. Provides spiritual protection.",
  "iconIndex": 41,
  "price": 150,
  "consumable": true,
  "damage": {"type": 0, "elementId": 0, "formula": "0", "variance": 0, "critical": false},
  "effects": [{"code": 32, "dataId": 70, "value1": 0, "value2": 0}],
  "repeats": 1,
  "tpGain": 0,
  "hitType": 0,
  "animationId": 0,
  "successRate": 100,
  "speed": 0,
  "scope": 1,
  "occasion": 0,
  "note": "Provides temporary protection against supernatural attacks",
  "etypeId": 0
},
{
  "id": 42,
  "name": "Confucian Righteousness Charm",
  "description": "A charm imbued with Confucian moral power. Strengthens resolve and moral clarity.",
  "iconIndex": 42,
  "price": 120,
  "consumable": true,
  "damage": {"type": 0, "elementId": 0, "formula": "0", "variance": 0, "critical": false},
  "effects": [{"code": 32, "dataId": 71, "value1": 0, "value2": 0}],
  "repeats": 1,
  "tpGain": 0,
  "hitType": 0,
  "animationId": 0,
  "successRate": 100,
  "speed": 0,
  "scope": 1,
  "occasion": 0,
  "note": "Enhances resistance to mental manipulation and fear",
  "etypeId": 0
},
{
  "id": 43,
  "name": "Buddhist Purification Incense",
  "description": "Sacred incense that purifies negative karma and spiritual corruption.",
  "iconIndex": 43,
  "price": 180,
  "consumable": true,
  "damage": {"type": 0, "elementId": 0, "formula": "0", "variance": 0, "critical": false},
  "effects": [{"code": 32, "dataId": 72, "value1": 0, "value2": 0}],
  "repeats": 1,
  "tpGain": 0,
  "hitType": 0,
  "animationId": 0,
  "successRate": 100,
  "speed": 0,
  "scope": 8,
  "occasion": 0,
  "note": "Removes negative status effects from all party members",
  "etypeId": 0
},
{
  "id": 50,
  "name": "Ancient Clue Fragment",
  "description": "A piece of evidence from an ancient mystery. May be important for investigations.",
  "iconIndex": 50,
  "price": 0,
  "consumable": false,
  "damage": {"type": 0, "elementId": 0, "formula": "0", "variance": 0, "critical": false},
  "effects": [],
  "repeats": 1,
  "tpGain": 0,
  "hitType": 0,
  "animationId": 0,
  "successRate": 100,
  "speed": 0,
  "scope": 0,
  "occasion": 3,
  "note": "Investigation item - used in deduction sequences",
  "etypeId": 0
},
{
  "id": 51,
  "name": "Witness Testimony",
  "description": "Written testimony from a witness. Contains important information for case resolution.",
  "iconIndex": 51,
  "price": 0,
  "consumable": false,
  "damage": {"type": 0, "elementId": 0, "formula": "0", "variance": 0, "critical": false},
  "effects": [],
  "repeats": 1,
  "tpGain": 0,
  "hitType": 0,
  "animationId": 0,
  "successRate": 100,
  "speed": 0,
  "scope": 0,
  "occasion": 3,
  "note": "Investigation item - key evidence for solving cases",
  "etypeId": 0
},
{
  "id": 52,
  "name": "Mysterious Letter",
  "description": "An encrypted letter containing secret information. Requires decoding skills to understand.",
  "iconIndex": 52,
  "price": 0,
  "consumable": false,
  "damage": {"type": 0, "elementId": 0, "formula": "0", "variance": 0, "critical": false},
  "effects": [],
  "repeats": 1,
  "tpGain": 0,
  "hitType": 0,
  "animationId": 0,
  "successRate": 100,
  "speed": 0,
  "scope": 0,
  "occasion": 3,
  "note": "Investigation item - requires Logic Analysis skill to decode",
  "etypeId": 0
},
{
  "id": 60,
  "name": "Gu Master's Poison Vial",
  "description": "A vial containing potent Gu poison. Dangerous but potentially useful for investigations.",
  "iconIndex": 60,
  "price": 800,
  "consumable": true,
  "damage": {"type": 1, "elementId": 5, "formula": "300", "variance": 10, "critical": false},
  "effects": [{"code": 32, "dataId": 4, "value1": 0, "value2": 0}],
  "repeats": 1,
  "tpGain": 0,
  "hitType": 2,
  "animationId": 0,
  "successRate": 90,
  "speed": 0,
  "scope": 1,
  "occasion": 1,
  "note": "Poison damage item - inflicts poison status",
  "etypeId": 0
},
{
  "id": 61,
  "name": "Warlock's Divination Crystal",
  "description": "A crystal used by warlocks for divination and prophecy. Reveals hidden information.",
  "iconIndex": 61,
  "price": 1200,
  "consumable": true,
  "damage": {"type": 0, "elementId": 0, "formula": "0", "variance": 0, "critical": false},
  "effects": [{"code": 32, "dataId": 73, "value1": 0, "value2": 0}],
  "repeats": 1,
  "tpGain": 0,
  "hitType": 0,
  "animationId": 0,
  "successRate": 100,
  "speed": 0,
  "scope": 0,
  "occasion": 0,
  "note": "Reveals hidden clues and future events",
  "etypeId": 0
},
{
  "id": 70,
  "name": "Imperial Edict",
  "description": "An official imperial decree. Carries the full authority of the Emperor.",
  "iconIndex": 70,
  "price": 0,
  "consumable": false,
  "damage": {"type": 0, "elementId": 0, "formula": "0", "variance": 0, "critical": false},
  "effects": [],
  "repeats": 1,
  "tpGain": 0,
  "hitType": 0,
  "animationId": 0,
  "successRate": 100,
  "speed": 0,
  "scope": 0,
  "occasion": 3,
  "note": "Ultimate authority item - overrides most obstacles",
  "etypeId": 0
},
{
  "id": 71,
  "name": "Realm Society Token",
  "description": "A mysterious token marking membership in the secretive Realm Society.",
  "iconIndex": 71,
  "price": 0,
  "consumable": false,
  "damage": {"type": 0, "elementId": 0, "formula": "0", "variance": 0, "critical": false},
  "effects": [],
  "repeats": 1,
  "tpGain": 0,
  "hitType": 0,
  "animationId": 0,
  "successRate": 100,
  "speed": 0,
  "scope": 0,
  "occasion": 3,
  "note": "Key item - grants access to secret society content",
  "etypeId": 0
}
]
